cnxarchive/__init__.py
cnxarchive/_version.py
cnxarchive/cache.py
cnxarchive/config.py
cnxarchive/database.py
cnxarchive/default-logging.yaml
cnxarchive/events.py
cnxarchive/logs.py
cnxarchive/search.py
cnxarchive/sitemap.py
cnxarchive/tweens.py
cnxarchive/data/common-english-words.txt
cnxarchive/scripts/__init__.py
cnxarchive/scripts/_utils.py
cnxarchive/scripts/hits_counter.py
cnxarchive/scripts/inject_resource.py
cnxarchive/scripts/export_epub/__init__.py
cnxarchive/scripts/export_epub/__main__.py
cnxarchive/scripts/export_epub/db.py
cnxarchive/scripts/export_epub/exceptions.py
cnxarchive/scripts/export_epub/main.py
cnxarchive/scripts/export_epub/modeling.py
cnxarchive/scripts/export_epub/sql/get-baked-content.sql
cnxarchive/scripts/export_epub/sql/get-content.sql
cnxarchive/scripts/export_epub/sql/get-file-info-in-context.sql
cnxarchive/scripts/export_epub/sql/get-file-info.sql
cnxarchive/scripts/export_epub/sql/get-file.sql
cnxarchive/scripts/export_epub/sql/get-metadata.sql
cnxarchive/scripts/export_epub/sql/get-registered-files-info.sql
cnxarchive/scripts/export_epub/sql/get-tree.sql
cnxarchive/scripts/export_epub/sql/get-type.sql
cnxarchive/scripts/export_epub/sql/verify-id-and-version.sql
cnxarchive/tests/.ci-testing.ini
cnxarchive/tests/__init__.py
cnxarchive/tests/docker-testing.ini
cnxarchive/tests/test_database.py
cnxarchive/tests/test_functional.py
cnxarchive/tests/test_routes.py
cnxarchive/tests/test_search.py
cnxarchive/tests/test_sitemap.py
cnxarchive/tests/test_utils.py
cnxarchive/tests/testing.ini
cnxarchive/tests/testing.py
cnxarchive/tests/data/README.rst
cnxarchive/tests/data/collection.xml
cnxarchive/tests/data/collection_minor_2.xml
cnxarchive/tests/data/collection_minor_3.xml
cnxarchive/tests/data/data.sql
cnxarchive/tests/data/e3d625fe.png
cnxarchive/tests/data/m10761-2.3.cnxml
cnxarchive/tests/data/m31947-1.3.cnxml
cnxarchive/tests/data/m42033-1.3.cnxml
cnxarchive/tests/data/m42033-1.3.html
cnxarchive/tests/data/m42119-1.3-modified.cnxml
cnx_archive-4.15.23.dist-info/LICENSE.txt
cnx_archive-4.15.23.dist-info/METADATA
cnx_archive-4.15.23.dist-info/WHEEL
cnx_archive-4.15.23.dist-info/entry_points.txt
cnx_archive-4.15.23.dist-info/top_level.txt
cnx_archive-4.15.23.dist-info/RECORD
