Metadata-Version: 2.1
Name: cnx-archive
Version: 4.15.23
Summary: An archive for Connexions documents.
Home-page: https://github.com/connexions/cnx-archive
Author: Connexions team
Author-email: info@cnx.org
License: LGPL, See also LICENSE.txt
Platform: UNKNOWN
Requires-Dist: certifi (==2021.5.30)
Requires-Dist: chardet (==4.0.0)
Requires-Dist: cnx-common (==1.3.6)
Requires-Dist: cnx-db (==3.5.3)
Requires-Dist: cnx-epub (==0.26.2)
Requires-Dist: cnx-query-grammar (==0.2.2)
Requires-Dist: cnx-transforms (==1.2.2)
Requires-Dist: hupper (==1.10.3)
Requires-Dist: idna (==2.10)
Requires-Dist: jinja2 (==2.11.3)
Requires-Dist: lxml (==4.4.3)
Requires-Dist: markupsafe (==1.1.1)
Requires-Dist: parsimonious (==0.8.1)
Requires-Dist: pastedeploy (==2.1.1)
Requires-Dist: plaster-pastedeploy (==0.7)
Requires-Dist: plaster (==1.0)
Requires-Dist: psycopg2 (==2.8.6)
Requires-Dist: pyramid-jinja2 (==2.8)
Requires-Dist: pyramid (==1.10.7)
Requires-Dist: python-memcached (==1.59)
Requires-Dist: python-slugify (==4.0.1)
Requires-Dist: pytz (==2021.1)
Requires-Dist: requests (==2.25.1)
Requires-Dist: rhaptos.cnxmlutils (==2.1.1)
Requires-Dist: six (==1.16.0)
Requires-Dist: sqlalchemy (==1.4.20)
Requires-Dist: text-unidecode (==1.3)
Requires-Dist: translationstring (==1.4)
Requires-Dist: tzlocal (==2.1)
Requires-Dist: urllib3 (==1.26.6)
Requires-Dist: venusian (==1.2.0)
Requires-Dist: waitress (==1.4.4)
Requires-Dist: webob (==1.8.7)
Requires-Dist: zope.deprecation (==4.4.0)
Requires-Dist: zope.interface (==5.4.0)
